[1,["e3zV+mk7dP6IhWa2aXJM1N","3482K9mZtLlYeUXF/77vWO","f7vibAnp5CbIv2gLqhrTJe","bdHXm5OTFMqbQ/kKZHLVA/"],["_textureSetter"],["cc.SpriteFrame"],0,[[[{"name":"wkdw_bat2_daijii4","rect":[0,0,66,66],"offset":[0,0],"originalSize":[66,66],"capInsets":[0,0,0,0]}],[0],0,[0],[0],[0]],[[{"name":"wkdw_bat2_daijii2","rect":[0,0,66,66],"offset":[0,0],"originalSize":[66,66],"capInsets":[0,0,0,0]}],[0],0,[0],[0],[1]],[[{"name":"wkdw_bat2_daijii1","rect":[0,0,66,66],"offset":[0,0],"originalSize":[66,66],"capInsets":[0,0,0,0]}],[0],0,[0],[0],[2]],[[{"name":"wkdw_bat2_daijii3","rect":[0,0,66,66],"offset":[0,0],"originalSize":[66,66],"capInsets":[0,0,0,0]}],[0],0,[0],[0],[3]]]]