[1,["78sCr5YyJJOph1bTHOO06S","694ljs76hHNa1DE53Jcmh2","e0gYe3H39J15HT4al8bAId","2dFK9tvsVJPrNmcWN5aL35","17petFRt1PFKUAWZHEUMIc","12hAYNcIBHroL3QRbEoML7","a5ETmx4z1BRZ4b+tv4MppO","45wtNiPTNIW7xQCrccnSAh","39s1TpUA1HQoKAqkZwavq1","ad5+eltQRKBJED2TUCHs22","acIxacYgJKsomYkyBke/iV","a2jkEO9WBLoYlvZFcPPKny","f5TnyAKFVMgpdNYP6s+2xF","3bN1fHKwJLI6eJl/CkimMt","41kA4wQ65KwIOcERQww82/","f7GMnlXNVCI5rsGCcwSY8A","6emmyddOpNIoMy3tuwEorx","e9BegJYstNbohcQagGdnKi","b7et6AJIFAv6P99lwtw1y0","93Wx4QEqdOWov3sl4TSYSq","85hIrcsCtF/4r9cfHN5FXN","48pA7XPEtFWKZbs+OXPJL0","1emA5YQvRGxJOdbR3TT0bZ","1ft7MvIJVDdJumoVL0Oedw","a81ugvWfdFobcZoaE8KGZ1","78vXD+tfpAhrt0ydSYQqbH","b68MBbiKNEIIotY141YJOj","60bJWbsslOJo8mPt0Sufce","14M5ZSQ9lKG4s/QnDEuIl4","b0KQ+VSyFHmZaCkOXy3cMl","9doPNy7/NA9JdRbmrVv5Z9","1bWB39uSFFLopJgnlOO69T","28b5URKEhMyaSlu8g63VRV","80H9HuC5NN3a6igzoxUHvG","50+aYzsaZPqqYFLdmtu24+","87lgsH17tNU5ctzxMJsA4c","fanOIVA/xHgozYP6EwS8Ta","1b1KZPvR9BprwdKjFkkATf","18jFaayc1FwathUebUeaeD","332HHdAnlDi7SPRnC9zg0/","15EOZtQS9B4bB70dbTCB/7","91RbfI6mhAp50J+4iOF6w6","b1Vo6U3JxEZqbt0OQgy69v","2crbqfYRdJHbIabUk0jt3b","2bTl/LO/RGeI0hBFbb8VW5","48gzZcRWdLdaMLFjmBSJVI"],["_textureSetter","value"],["cc.SpriteFrame",["cc.AnimationClip",["_name","_duration","sample","events","curveData"],-1,11]],[[1,0,1,2,3,4,5]],[[[{"name":"baoxiang21","rect":[0,0,50,77],"offset":[0,0],"originalSize":[50,77],"capInsets":[0,0,0,0]}],[0],0,[0],[0],[0]],[[{"name":"baoxiang15","rect":[0,0,50,77],"offset":[0,0],"originalSize":[50,77],"capInsets":[0,0,0,0]}],[0],0,[0],[0],[1]],[[{"name":"baoxiang16","rect":[0,0,50,77],"offset":[0,0],"originalSize":[50,77],"capInsets":[0,0,0,0]}],[0],0,[0],[0],[2]],[[{"name":"baoxiang1","rect":[0,0,50,77],"offset":[0,0],"originalSize":[50,77],"capInsets":[0,0,0,0]}],[0],0,[0],[0],[3]],[[{"name":"baoxiang6","rect":[0,0,50,77],"offset":[0,0],"originalSize":[50,77],"capInsets":[0,0,0,0]}],[0],0,[0],[0],[4]],[[{"name":"baoxiang7","rect":[0,0,50,77],"offset":[0,0],"originalSize":[50,77],"capInsets":[0,0,0,0]}],[0],0,[0],[0],[5]],[[{"name":"baoxiang14","rect":[0,0,50,77],"offset":[0,0],"originalSize":[50,77],"capInsets":[0,0,0,0]}],[0],0,[0],[0],[6]],[[{"name":"baoxiang20","rect":[0,0,50,77],"offset":[0,0],"originalSize":[50,77],"capInsets":[0,0,0,0]}],[0],0,[0],[0],[7]],[[[0,"chest2",2.3,10,[{"frame":1.4,"func":"A_open","params":[]}],[{},"paths",11,[{},"Sprite",11,[{"props":{"opacity":[{"frame":0,"value":255},{"frame":2,"value":255},{"frame":2.3,"value":0}]}},"comps",11,[{},"cc.Sprite",11,[{},"spriteFrame",12,[[[{"frame":0},"value",6,0],[{"frame":0.1},"value",6,1],[{"frame":0.2},"value",6,2],[{"frame":0.3},"value",6,3],[{"frame":0.4},"value",6,4],[{"frame":0.5},"value",6,5],[{"frame":0.6},"value",6,6],[{"frame":0.7},"value",6,7],[{"frame":0.8},"value",6,8],[{"frame":0.9},"value",6,9],[{"frame":1},"value",6,10],[{"frame":1.1},"value",6,11],[{"frame":1.2},"value",6,12],[{"frame":1.3},"value",6,13],[{"frame":1.4},"value",6,14],[{"frame":1.5},"value",6,15],[{"frame":1.6},"value",6,16],[{"frame":1.7},"value",6,17],[{"frame":1.8},"value",6,18],[{"frame":1.9},"value",6,19],[{"frame":2},"value",6,20],[{"frame":2.1},"value",6,21],[{"frame":2.2},"value",6,22]],11,11,11,11,11,11,11,11,11,11,11,11,11,11,11,11,11,11,11,11,11,11,11]]]]]]]],0,0,[0,0,0,0,0,0,0,0,0,0,0,0,0,0,0,0,0,0,0,0,0,0,0],[1,1,1,1,1,1,1,1,1,1,1,1,1,1,1,1,1,1,1,1,1,1,1],[8,9,10,11,12,13,14,15,16,17,18,19,20,21,22,23,24,25,26,27,28,29,30]],[[{"name":"baoxiang9","rect":[0,0,50,77],"offset":[0,0],"originalSize":[50,77],"capInsets":[0,0,0,0]}],[0],0,[0],[0],[31]],[[{"name":"baoxiang18","rect":[0,0,50,77],"offset":[0,0],"originalSize":[50,77],"capInsets":[0,0,0,0]}],[0],0,[0],[0],[32]],[[{"name":"baoxiang13","rect":[0,0,50,77],"offset":[0,0],"originalSize":[50,77],"capInsets":[0,0,0,0]}],[0],0,[0],[0],[33]],[[{"name":"baoxiang12","rect":[0,0,50,77],"offset":[0,0],"originalSize":[50,77],"capInsets":[0,0,0,0]}],[0],0,[0],[0],[34]],[[{"name":"baoxiang23","rect":[0,0,50,77],"offset":[0,0],"originalSize":[50,77],"capInsets":[0,0,0,0]}],[0],0,[0],[0],[35]],[[{"name":"baoxiang4","rect":[0,0,50,77],"offset":[0,0],"originalSize":[50,77],"capInsets":[0,0,0,0]}],[0],0,[0],[0],[36]],[[{"name":"baoxiang17","rect":[0,0,50,77],"offset":[0,0],"originalSize":[50,77],"capInsets":[0,0,0,0]}],[0],0,[0],[0],[37]],[[{"name":"baoxiang3","rect":[0,0,50,77],"offset":[0,0],"originalSize":[50,77],"capInsets":[0,0,0,0]}],[0],0,[0],[0],[38]],[[{"name":"baoxiang2","rect":[0,0,50,77],"offset":[0,0],"originalSize":[50,77],"capInsets":[0,0,0,0]}],[0],0,[0],[0],[39]],[[{"name":"baoxiang22","rect":[0,0,50,77],"offset":[0,0],"originalSize":[50,77],"capInsets":[0,0,0,0]}],[0],0,[0],[0],[40]],[[{"name":"baoxiang19","rect":[0,0,50,77],"offset":[0,0],"originalSize":[50,77],"capInsets":[0,0,0,0]}],[0],0,[0],[0],[41]],[[{"name":"baoxiang11","rect":[0,0,50,77],"offset":[0,0],"originalSize":[50,77],"capInsets":[0,0,0,0]}],[0],0,[0],[0],[42]],[[{"name":"baoxiang10","rect":[0,0,50,77],"offset":[0,0],"originalSize":[50,77],"capInsets":[0,0,0,0]}],[0],0,[0],[0],[43]],[[{"name":"baoxiang5","rect":[0,0,50,77],"offset":[0,0],"originalSize":[50,77],"capInsets":[0,0,0,0]}],[0],0,[0],[0],[44]],[[{"name":"baoxiang8","rect":[0,0,50,77],"offset":[0,0],"originalSize":[50,77],"capInsets":[0,0,0,0]}],[0],0,[0],[0],[45]]]]